open_petro_elastic/__init__.py
open_petro_elastic/__main__.py
open_petro_elastic/float_vectorize.py
open_petro_elastic/config/__init__.py
open_petro_elastic/config/coefficients.py
open_petro_elastic/config/constituent.py
open_petro_elastic/config/depth_trend.py
open_petro_elastic/config/dry_rock.py
open_petro_elastic/config/fluid_model_providers.py
open_petro_elastic/config/fluids.py
open_petro_elastic/config/input.py
open_petro_elastic/config/material_type.py
open_petro_elastic/config/minerals.py
open_petro_elastic/config/model.py
open_petro_elastic/config/pressure.py
open_petro_elastic/config/pressure_dependency.py
open_petro_elastic/config/pydantic_config.py
open_petro_elastic/config/vector_type.py
open_petro_elastic/material/__init__.py
open_petro_elastic/material/conversions.py
open_petro_elastic/material/fluid.py
open_petro_elastic/material/hashin_shtrikman.py
open_petro_elastic/material/material.py
open_petro_elastic/material/seismic_velocity.py
open_petro_elastic/material/batzle_wang/__init__.py
open_petro_elastic/material/batzle_wang/brine_properties.py
open_petro_elastic/material/batzle_wang/hydro_carbon_gas.py
open_petro_elastic/material/batzle_wang/ideal_gas.py
open_petro_elastic/material/batzle_wang/oil_properties.py
open_petro_elastic/material/batzle_wang/water_properties.py
open_petro_elastic/material/sandstone/__init__.py
open_petro_elastic/material/sandstone/constant_cement.py
open_petro_elastic/material/sandstone/contact_cement.py
open_petro_elastic/material/sandstone/friable_sand.py
open_petro_elastic/material/sandstone/hertz_mindlin.py
open_petro_elastic/material/sandstone/murphy_coordination_number.py
open_petro_elastic/material/sandstone/patchy_cement.py
open_petro_elastic/material/span_wagner/__init__.py
open_petro_elastic/material/span_wagner/carbon_dioxide.py
open_petro_elastic/material/span_wagner/coefficients.py
open_petro_elastic/material/span_wagner/equations.py
open_petro_elastic/material/span_wagner/tables/__init__.py
open_petro_elastic-1.4.1.dist-info/LICENSE
open_petro_elastic-1.4.1.dist-info/METADATA
open_petro_elastic-1.4.1.dist-info/WHEEL
open_petro_elastic-1.4.1.dist-info/entry_points.txt
open_petro_elastic-1.4.1.dist-info/top_level.txt
open_petro_elastic-1.4.1.dist-info/RECORD
