Metadata-Version: 2.2
Name: open_petro_elastic
Version: 1.4.1
Summary: Utility for calculating elastic properties of rocks and fluids.
Author-email: Equinor <fg_sib-scout@equinor.com>
License: GNU LESSER GENERAL PUBLIC LICENSE
Project-URL: documentation, https://equinor.github.io/open_petro_elastic
Project-URL: repository, https://github.com/equinor/open_petro_elastic
Keywords: geophysics,rock physics,materials science
Classifier: Development Status :: 3 - Alpha
Classifier: License :: OSI Approved :: GNU Lesser General Public License v3 or later (LGPLv3+)
Classifier: Intended Audience :: Science/Research
Classifier: Topic :: Scientific/Engineering :: Hydrology
Classifier: Topic :: Scientific/Engineering :: Physics
Classifier: Natural Language :: English
Classifier: Operating System :: OS Independent
Classifier: Programming Language :: Python :: 3.8
Classifier: Programming Language :: Python :: 3.9
Classifier: Programming Language :: Python :: 3.10
Classifier: Programming Language :: Python :: 3.11
Classifier: Programming Language :: Python :: 3.12
Requires-Python: >=3.8
License-File: LICENSE
Requires-Dist: numpy
Requires-Dist: scipy
Requires-Dist: pyyaml
Requires-Dist: pandas
Requires-Dist: pydantic
Requires-Dist: sympy
Requires-Dist: typing_extensions
Provides-Extra: test
Requires-Dist: pytest; extra == "test"
Requires-Dist: syrupy; extra == "test"
Requires-Dist: hypothesis; extra == "test"
Requires-Dist: matplotlib; extra == "test"
Requires-Dist: pillow>=10.0.0; extra == "test"
Requires-Dist: Flake8-pyproject; extra == "test"
Provides-Extra: docs
Requires-Dist: sphinx; extra == "docs"
Requires-Dist: sphinx-rtd-theme; extra == "docs"
Requires-Dist: sphinx-argparse; extra == "docs"
Requires-Dist: matplotlib; extra == "docs"
Requires-Dist: recommonmark; extra == "docs"
Requires-Dist: pygments-csv-lexer; extra == "docs"
Provides-Extra: dev
Requires-Dist: build; extra == "dev"
Requires-Dist: setuptools; extra == "dev"
Requires-Dist: ruff; extra == "dev"
Requires-Dist: mypy; extra == "dev"
